routemaster_sdk/__init__.py
routemaster_sdk/api.py
routemaster_sdk/conftest.py
routemaster_sdk/exceptions.py
routemaster_sdk/types.py
routemaster_sdk-0.0.1.dist-info/DESCRIPTION.rst
routemaster_sdk-0.0.1.dist-info/METADATA
routemaster_sdk-0.0.1.dist-info/RECORD
routemaster_sdk-0.0.1.dist-info/WHEEL
routemaster_sdk-0.0.1.dist-info/metadata.json
routemaster_sdk-0.0.1.dist-info/top_level.txt
