Metadata-Version: 2.0
Name: routemaster-sdk
Version: 0.0.1
Summary: SDK for Routemaster (state machines as a service).
Home-page: https://github.com/thread/routemaster-sdk
Author: Thread
Author-email: tech@thread.com
License: MIT
Platform: UNKNOWN
Classifier: Development Status :: 2 - Pre-Alpha
Classifier: Environment :: Console
Classifier: Natural Language :: English
Classifier: Operating System :: POSIX
Classifier: Programming Language :: Python
Classifier: Programming Language :: Python :: 3 :: Only
Classifier: Programming Language :: Python :: 3.5
Classifier: Programming Language :: Python :: 3.6
Classifier: Topic :: Office/Business
Requires-Dist: requests
